_cheetah.abi3.so
yelp_cheetah-0.19.1.dist-info/top_level.txt
yelp_cheetah-0.19.1.dist-info/METADATA
yelp_cheetah-0.19.1.dist-info/RECORD
yelp_cheetah-0.19.1.dist-info/LICENSE
yelp_cheetah-0.19.1.dist-info/WHEEL
yelp_cheetah-0.19.1.dist-info/entry_points.txt
Cheetah/legacy_parser.py
Cheetah/SourceReader.py
Cheetah/SettingsManager.py
Cheetah/legacy_compiler.py
Cheetah/Template.py
Cheetah/partial_template.py
Cheetah/DummyTransaction.py
Cheetah/compile.py
Cheetah/cheetah_compile.py
Cheetah/__init__.py
Cheetah/NameMapper.py
Cheetah/ast_utils.py
Cheetah/filters.py
Cheetah/setuptools_support.py
Cheetah/testing/all_partials_tested.py
Cheetah/testing/partial_template_test_case.py
Cheetah/testing/__init__.py
